metroprojectile/__init__.py
metroprojectile/ui.py
mpui-0.1.0.dist-info/METADATA
mpui-0.1.0.dist-info/WHEEL
mpui-0.1.0.dist-info/top_level.txt
mpui-0.1.0.dist-info/RECORD
